{"contest":{"contest_group":"U.S. Representative","contest_id":167,"contest_type":"candidate","district":null,"election_id":1,"measure_pass_rate":null,"measure_text":null,"office":"UNITED STATES REPRESENTATIVE, 38th District","source":"la_county","vote_for":null},"drops":[{"batch_id":1603,"batch_ts":"2026-06-06T16:50:09","candidates":[{"candidate_id":623,"incumbent":null,"is_first_drop":false,"name":"ERIK LUTZ","new_votes":162,"new_votes_pct":2.69,"party":"Democratic","pct_delta":-0.03,"vote_pct":3.06,"votes":2411},{"candidate_id":624,"incumbent":null,"is_first_drop":false,"name":"HILDA SOLIS","new_votes":3742,"new_votes_pct":62.14,"party":"Democratic","pct_delta":0.66,"vote_pct":54.18,"votes":42650},{"candidate_id":625,"incumbent":null,"is_first_drop":false,"name":"MONICA M. SANCHEZ","new_votes":934,"new_votes_pct":15.51,"party":"Democratic","pct_delta":0.15,"vote_pct":13.66,"votes":10754},{"candidate_id":626,"incumbent":null,"is_first_drop":false,"name":"PEDRO ANTONIO CASAS","new_votes":1184,"new_votes_pct":19.66,"party":"Republican","pct_delta":-0.78,"vote_pct":29.1,"votes":22911}],"drop_total":78726,"new_votes_in_drop":6022,"reporting_pct":null,"source_file":"LA_County_Election_4338-2026-06-06T16-50-09.18.json"},{"batch_id":1530,"batch_ts":"2026-06-05T16:38:45","candidates":[{"candidate_id":623,"incumbent":null,"is_first_drop":false,"name":"ERIK LUTZ","new_votes":136,"new_votes_pct":2.4,"party":"Democratic","pct_delta":-0.06,"vote_pct":3.09,"votes":2249},{"candidate_id":624,"incumbent":null,"is_first_drop":false,"name":"HILDA SOLIS","new_votes":3591,"new_votes_pct":63.26,"party":"Democratic","pct_delta":0.83,"vote_pct":53.52,"votes":38908},{"candidate_id":625,"incumbent":null,"is_first_drop":false,"name":"MONICA M. SANCHEZ","new_votes":922,"new_votes_pct":16.24,"party":"Democratic","pct_delta":0.23,"vote_pct":13.51,"votes":9820},{"candidate_id":626,"incumbent":null,"is_first_drop":false,"name":"PEDRO ANTONIO CASAS","new_votes":1028,"new_votes_pct":18.11,"party":"Republican","pct_delta":-1.0,"vote_pct":29.88,"votes":21727}],"drop_total":72704,"new_votes_in_drop":5677,"reporting_pct":null,"source_file":"LA_County_Election_4338-2026-06-05T16-38-45.853.json"},{"batch_id":1445,"batch_ts":"2026-06-04T16:11:55","candidates":[{"candidate_id":623,"incumbent":null,"is_first_drop":false,"name":"ERIK LUTZ","new_votes":82,"new_votes_pct":2.24,"party":"Democratic","pct_delta":-0.05,"vote_pct":3.15,"votes":2113},{"candidate_id":624,"incumbent":null,"is_first_drop":false,"name":"HILDA SOLIS","new_votes":2319,"new_votes_pct":63.45,"party":"Democratic","pct_delta":0.62,"vote_pct":52.69,"votes":35317},{"candidate_id":625,"incumbent":null,"is_first_drop":false,"name":"MONICA M. SANCHEZ","new_votes":526,"new_votes_pct":14.39,"party":"Democratic","pct_delta":0.07,"vote_pct":13.28,"votes":8898},{"candidate_id":626,"incumbent":null,"is_first_drop":false,"name":"PEDRO ANTONIO CASAS","new_votes":728,"new_votes_pct":19.92,"party":"Republican","pct_delta":-0.63,"vote_pct":30.88,"votes":20699}],"drop_total":67027,"new_votes_in_drop":3655,"reporting_pct":null,"source_file":"LA_County_Election_4338-2026-06-04T16-11-55.48.json"},{"batch_id":1324,"batch_ts":"2026-06-03T16:07:14","candidates":[{"candidate_id":623,"incumbent":null,"is_first_drop":false,"name":"ERIK LUTZ","new_votes":65,"new_votes_pct":2.29,"party":"Democratic","pct_delta":-0.05,"vote_pct":3.2,"votes":2031},{"candidate_id":624,"incumbent":null,"is_first_drop":false,"name":"HILDA SOLIS","new_votes":1625,"new_votes_pct":57.2,"party":"Democratic","pct_delta":0.24,"vote_pct":52.07,"votes":32998},{"candidate_id":625,"incumbent":null,"is_first_drop":false,"name":"MONICA M. SANCHEZ","new_votes":365,"new_votes_pct":12.85,"party":"Democratic","pct_delta":-0.02,"vote_pct":13.21,"votes":8372},{"candidate_id":626,"incumbent":null,"is_first_drop":false,"name":"PEDRO ANTONIO CASAS","new_votes":786,"new_votes_pct":27.67,"party":"Republican","pct_delta":-0.18,"vote_pct":31.51,"votes":19971}],"drop_total":63372,"new_votes_in_drop":2841,"reporting_pct":null,"source_file":"LA_County_Election_4338-2026-06-03T16-07-14.883.json"},{"batch_id":1167,"batch_ts":"2026-06-03T02:08:27","candidates":[{"candidate_id":623,"incumbent":null,"is_first_drop":false,"name":"ERIK LUTZ","new_votes":5,"new_votes_pct":2.33,"party":"Democratic","pct_delta":0.0,"vote_pct":3.25,"votes":1966},{"candidate_id":624,"incumbent":null,"is_first_drop":false,"name":"HILDA SOLIS","new_votes":129,"new_votes_pct":60.0,"party":"Democratic","pct_delta":0.03,"vote_pct":51.83,"votes":31373},{"candidate_id":625,"incumbent":null,"is_first_drop":false,"name":"MONICA M. SANCHEZ","new_votes":41,"new_votes_pct":19.07,"party":"Democratic","pct_delta":0.02,"vote_pct":13.23,"votes":8007},{"candidate_id":626,"incumbent":null,"is_first_drop":false,"name":"PEDRO ANTONIO CASAS","new_votes":40,"new_votes_pct":18.6,"party":"Republican","pct_delta":-0.05,"vote_pct":31.69,"votes":19185}],"drop_total":60531,"new_votes_in_drop":215,"reporting_pct":null,"source_file":"LA_County_Election_4338-2026-06-03T02-08-27.123.json"},{"batch_id":1142,"batch_ts":"2026-06-03T01:27:31","candidates":[{"candidate_id":623,"incumbent":null,"is_first_drop":false,"name":"ERIK LUTZ","new_votes":32,"new_votes_pct":2.5,"party":"Democratic","pct_delta":-0.02,"vote_pct":3.25,"votes":1961},{"candidate_id":624,"incumbent":null,"is_first_drop":false,"name":"HILDA SOLIS","new_votes":613,"new_votes_pct":47.97,"party":"Democratic","pct_delta":-0.08,"vote_pct":51.8,"votes":31244},{"candidate_id":625,"incumbent":null,"is_first_drop":false,"name":"MONICA M. SANCHEZ","new_votes":153,"new_votes_pct":11.97,"party":"Democratic","pct_delta":-0.02,"vote_pct":13.21,"votes":7966},{"candidate_id":626,"incumbent":null,"is_first_drop":false,"name":"PEDRO ANTONIO CASAS","new_votes":480,"new_votes_pct":37.56,"party":"Republican","pct_delta":0.12,"vote_pct":31.74,"votes":19145}],"drop_total":60316,"new_votes_in_drop":1278,"reporting_pct":null,"source_file":"LA_County_Election_4338-2026-06-03T01-27-31.423.json"},{"batch_id":1021,"batch_ts":"2026-06-03T00:51:34","candidates":[{"candidate_id":623,"incumbent":null,"is_first_drop":false,"name":"ERIK LUTZ","new_votes":57,"new_votes_pct":3.7,"party":"Democratic","pct_delta":0.01,"vote_pct":3.27,"votes":1929},{"candidate_id":624,"incumbent":null,"is_first_drop":false,"name":"HILDA SOLIS","new_votes":608,"new_votes_pct":39.45,"party":"Democratic","pct_delta":-0.34,"vote_pct":51.88,"votes":30631},{"candidate_id":625,"incumbent":null,"is_first_drop":false,"name":"MONICA M. SANCHEZ","new_votes":149,"new_votes_pct":9.67,"party":"Democratic","pct_delta":-0.1,"vote_pct":13.23,"votes":7813},{"candidate_id":626,"incumbent":null,"is_first_drop":false,"name":"PEDRO ANTONIO CASAS","new_votes":727,"new_votes_pct":47.18,"party":"Republican","pct_delta":0.42,"vote_pct":31.62,"votes":18665}],"drop_total":59038,"new_votes_in_drop":1541,"reporting_pct":null,"source_file":"LA_County_Election_4338-2026-06-03T00-51-34.797.json"},{"batch_id":984,"batch_ts":"2026-06-03T00:11:21","candidates":[{"candidate_id":623,"incumbent":null,"is_first_drop":false,"name":"ERIK LUTZ","new_votes":67,"new_votes_pct":2.6,"party":"Democratic","pct_delta":-0.03,"vote_pct":3.26,"votes":1872},{"candidate_id":624,"incumbent":null,"is_first_drop":false,"name":"HILDA SOLIS","new_votes":1437,"new_votes_pct":55.72,"party":"Democratic","pct_delta":0.17,"vote_pct":52.22,"votes":30023},{"candidate_id":625,"incumbent":null,"is_first_drop":false,"name":"MONICA M. SANCHEZ","new_votes":381,"new_votes_pct":14.77,"party":"Democratic","pct_delta":0.07,"vote_pct":13.33,"votes":7664},{"candidate_id":626,"incumbent":null,"is_first_drop":false,"name":"PEDRO ANTONIO CASAS","new_votes":694,"new_votes_pct":26.91,"party":"Republican","pct_delta":-0.2,"vote_pct":31.2,"votes":17938}],"drop_total":57497,"new_votes_in_drop":2579,"reporting_pct":null,"source_file":"LA_County_Election_4338-2026-06-03T00-11-21.433.json"},{"batch_id":407,"batch_ts":"2026-06-02T23:29:15","candidates":[{"candidate_id":623,"incumbent":null,"is_first_drop":false,"name":"ERIK LUTZ","new_votes":223,"new_votes_pct":3.93,"party":"Democratic","pct_delta":0.08,"vote_pct":3.29,"votes":1805},{"candidate_id":624,"incumbent":null,"is_first_drop":false,"name":"HILDA SOLIS","new_votes":2520,"new_votes_pct":44.37,"party":"Democratic","pct_delta":-0.89,"vote_pct":52.05,"votes":28586},{"candidate_id":625,"incumbent":null,"is_first_drop":false,"name":"MONICA M. SANCHEZ","new_votes":750,"new_votes_pct":13.2,"party":"Democratic","pct_delta":-0.01,"vote_pct":13.26,"votes":7283},{"candidate_id":626,"incumbent":null,"is_first_drop":false,"name":"PEDRO ANTONIO CASAS","new_votes":2187,"new_votes_pct":38.5,"party":"Republican","pct_delta":0.82,"vote_pct":31.4,"votes":17244}],"drop_total":54918,"new_votes_in_drop":5680,"reporting_pct":null,"source_file":"LA_County_Election_4338-2026-06-02T23-29-15.387.json"},{"batch_id":406,"batch_ts":"2026-06-02T22:50:33","candidates":[{"candidate_id":623,"incumbent":null,"is_first_drop":false,"name":"ERIK LUTZ","new_votes":56,"new_votes_pct":2.33,"party":"Democratic","pct_delta":-0.05,"vote_pct":3.21,"votes":1582},{"candidate_id":624,"incumbent":null,"is_first_drop":false,"name":"HILDA SOLIS","new_votes":1159,"new_votes_pct":48.21,"party":"Democratic","pct_delta":-0.24,"vote_pct":52.94,"votes":26066},{"candidate_id":625,"incumbent":null,"is_first_drop":false,"name":"MONICA M. SANCHEZ","new_votes":329,"new_votes_pct":13.69,"party":"Democratic","pct_delta":0.02,"vote_pct":13.27,"votes":6533},{"candidate_id":626,"incumbent":null,"is_first_drop":false,"name":"PEDRO ANTONIO CASAS","new_votes":860,"new_votes_pct":35.77,"party":"Republican","pct_delta":0.27,"vote_pct":30.58,"votes":15057}],"drop_total":49238,"new_votes_in_drop":2404,"reporting_pct":null,"source_file":"LA_County_Election_4338-2026-06-02T22-50-33.983.json"},{"batch_id":321,"batch_ts":"2026-06-02T22:17:30","candidates":[{"candidate_id":623,"incumbent":null,"is_first_drop":false,"name":"ERIK LUTZ","new_votes":41,"new_votes_pct":2.68,"party":"Democratic","pct_delta":-0.02,"vote_pct":3.26,"votes":1526},{"candidate_id":624,"incumbent":null,"is_first_drop":false,"name":"HILDA SOLIS","new_votes":853,"new_votes_pct":55.82,"party":"Democratic","pct_delta":0.09,"vote_pct":53.18,"votes":24907},{"candidate_id":625,"incumbent":null,"is_first_drop":false,"name":"MONICA M. SANCHEZ","new_votes":205,"new_votes_pct":13.42,"party":"Democratic","pct_delta":0.01,"vote_pct":13.25,"votes":6204},{"candidate_id":626,"incumbent":null,"is_first_drop":false,"name":"PEDRO ANTONIO CASAS","new_votes":429,"new_votes_pct":28.08,"party":"Republican","pct_delta":-0.08,"vote_pct":30.31,"votes":14197}],"drop_total":46834,"new_votes_in_drop":1528,"reporting_pct":null,"source_file":"LA_County_Election_4338-2026-06-02T22-17-30.85.json"},{"batch_id":140,"batch_ts":"2026-06-02T21:33:40","candidates":[{"candidate_id":623,"incumbent":null,"is_first_drop":false,"name":"ERIK LUTZ","new_votes":18,"new_votes_pct":4.03,"party":"Democratic","pct_delta":0.01,"vote_pct":3.28,"votes":1485},{"candidate_id":624,"incumbent":null,"is_first_drop":false,"name":"HILDA SOLIS","new_votes":280,"new_votes_pct":62.64,"party":"Democratic","pct_delta":0.09,"vote_pct":53.09,"votes":24054},{"candidate_id":625,"incumbent":null,"is_first_drop":false,"name":"MONICA M. SANCHEZ","new_votes":52,"new_votes_pct":11.63,"party":"Democratic","pct_delta":-0.02,"vote_pct":13.24,"votes":5999},{"candidate_id":626,"incumbent":null,"is_first_drop":false,"name":"PEDRO ANTONIO CASAS","new_votes":97,"new_votes_pct":21.7,"party":"Republican","pct_delta":-0.09,"vote_pct":30.39,"votes":13768}],"drop_total":45306,"new_votes_in_drop":447,"reporting_pct":null,"source_file":"LA_County_Election_4338-2026-06-02T21-33-40.73.json"},{"batch_id":139,"batch_ts":"2026-06-02T21:18:00","candidates":[{"candidate_id":623,"incumbent":null,"is_first_drop":false,"name":"ERIK LUTZ","new_votes":10,"new_votes_pct":2.65,"party":"Democratic","pct_delta":-0.01,"vote_pct":3.27,"votes":1467},{"candidate_id":624,"incumbent":null,"is_first_drop":false,"name":"HILDA SOLIS","new_votes":217,"new_votes_pct":57.56,"party":"Democratic","pct_delta":0.04,"vote_pct":53.0,"votes":23774},{"candidate_id":625,"incumbent":null,"is_first_drop":false,"name":"MONICA M. SANCHEZ","new_votes":49,"new_votes_pct":13.0,"party":"Democratic","pct_delta":0.0,"vote_pct":13.26,"votes":5947},{"candidate_id":626,"incumbent":null,"is_first_drop":false,"name":"PEDRO ANTONIO CASAS","new_votes":101,"new_votes_pct":26.79,"party":"Republican","pct_delta":-0.03,"vote_pct":30.48,"votes":13671}],"drop_total":44859,"new_votes_in_drop":377,"reporting_pct":null,"source_file":"LA_County_Election_4338-2026-06-02T21-18-00.383.json"},{"batch_id":90,"batch_ts":"2026-06-02T20:48:40","candidates":[{"candidate_id":623,"incumbent":null,"is_first_drop":false,"name":"ERIK LUTZ","new_votes":11,"new_votes_pct":2.55,"party":"Democratic","pct_delta":0.0,"vote_pct":3.28,"votes":1457},{"candidate_id":624,"incumbent":null,"is_first_drop":false,"name":"HILDA SOLIS","new_votes":265,"new_votes_pct":61.34,"party":"Democratic","pct_delta":0.08,"vote_pct":52.96,"votes":23557},{"candidate_id":625,"incumbent":null,"is_first_drop":false,"name":"MONICA M. SANCHEZ","new_votes":60,"new_votes_pct":13.89,"party":"Democratic","pct_delta":0.01,"vote_pct":13.26,"votes":5898},{"candidate_id":626,"incumbent":null,"is_first_drop":false,"name":"PEDRO ANTONIO CASAS","new_votes":96,"new_votes_pct":22.22,"party":"Republican","pct_delta":-0.08,"vote_pct":30.51,"votes":13570}],"drop_total":44482,"new_votes_in_drop":432,"reporting_pct":null,"source_file":"LA_County_Election_4338-2026-06-02T20-48-40.927.json"},{"batch_id":16,"batch_ts":"2026-06-02T20:31:50","candidates":[{"candidate_id":623,"incumbent":null,"is_first_drop":false,"name":"ERIK LUTZ","new_votes":155,"new_votes_pct":2.76,"party":"Democratic","pct_delta":-0.08,"vote_pct":3.28,"votes":1446},{"candidate_id":624,"incumbent":null,"is_first_drop":false,"name":"HILDA SOLIS","new_votes":2341,"new_votes_pct":41.63,"party":"Democratic","pct_delta":-1.64,"vote_pct":52.88,"votes":23292},{"candidate_id":625,"incumbent":null,"is_first_drop":false,"name":"MONICA M. SANCHEZ","new_votes":656,"new_votes_pct":11.66,"party":"Democratic","pct_delta":-0.24,"vote_pct":13.25,"votes":5838},{"candidate_id":626,"incumbent":null,"is_first_drop":false,"name":"PEDRO ANTONIO CASAS","new_votes":2472,"new_votes_pct":43.95,"party":"Republican","pct_delta":1.96,"vote_pct":30.59,"votes":13474}],"drop_total":44050,"new_votes_in_drop":5624,"reporting_pct":null,"source_file":"LA_County_Election_4338-2026-06-02T20-31-50.377.json"},{"batch_id":15,"batch_ts":"2026-06-02T20:15:15","candidates":[{"candidate_id":623,"incumbent":null,"is_first_drop":false,"name":"ERIK LUTZ","new_votes":1291,"new_votes_pct":3.36,"party":"Democratic","pct_delta":3.36,"vote_pct":3.36,"votes":1291},{"candidate_id":624,"incumbent":null,"is_first_drop":false,"name":"HILDA SOLIS","new_votes":20951,"new_votes_pct":54.52,"party":"Democratic","pct_delta":54.52,"vote_pct":54.52,"votes":20951},{"candidate_id":625,"incumbent":null,"is_first_drop":false,"name":"MONICA M. SANCHEZ","new_votes":5182,"new_votes_pct":13.49,"party":"Democratic","pct_delta":13.49,"vote_pct":13.49,"votes":5182},{"candidate_id":626,"incumbent":null,"is_first_drop":false,"name":"PEDRO ANTONIO CASAS","new_votes":11002,"new_votes_pct":28.63,"party":"Republican","pct_delta":28.63,"vote_pct":28.63,"votes":11002}],"drop_total":38426,"new_votes_in_drop":38426,"reporting_pct":null,"source_file":"LA_County_Election_4338-2026-06-02T20-15-15.75.json"},{"batch_id":2,"batch_ts":"2026-05-26T16:54:13","candidates":[{"candidate_id":623,"incumbent":null,"is_first_drop":true,"name":"ERIK LUTZ","new_votes":0,"new_votes_pct":0.0,"party":"Democratic","pct_delta":0.0,"vote_pct":0.0,"votes":0},{"candidate_id":624,"incumbent":null,"is_first_drop":true,"name":"HILDA SOLIS","new_votes":0,"new_votes_pct":0.0,"party":"Democratic","pct_delta":0.0,"vote_pct":0.0,"votes":0},{"candidate_id":625,"incumbent":null,"is_first_drop":true,"name":"MONICA M. SANCHEZ","new_votes":0,"new_votes_pct":0.0,"party":"Democratic","pct_delta":0.0,"vote_pct":0.0,"votes":0},{"candidate_id":626,"incumbent":null,"is_first_drop":true,"name":"PEDRO ANTONIO CASAS","new_votes":0,"new_votes_pct":0.0,"party":"Republican","pct_delta":0.0,"vote_pct":0.0,"votes":0}],"drop_total":0,"new_votes_in_drop":0,"reporting_pct":null,"source_file":"LA_County_Election_4338-2026-05-26T16-54-13.63.json"}]}