{"contest":{"contest_group":"Cities","contest_id":36,"contest_type":"measure","district":null,"election_id":1,"measure_pass_rate":"Majority of votes cast","measure_text":"Keep La Puente Sales Tax Revenues Local Measure. To protect La Puente's funding for public safety; street/sidewalk maintenance/repair; park maintenance/enhancements; youth/senior programs and any other governmental purposes and prevent the County of Los Angeles and other taxing agencies from seizing additional sales tax revenues generated in La Puente for themselves, shall La Puente's 1/2% transactions (sales) and use tax be increased to 1% raising an additional $3.6 million annually, subject to the ability to suspend application of the increased rate? Supporters: Mayor Klinakis; Mayor Pro Tem Mu\u00f1oz; Councilmember Argudo; Councilmember Mendoza; Councilmember Qui\u00f1ones Opponents: None submitted.","office":"CITY OF LA PUENTE SPECIAL MUNICIPAL ELECTION - MEASURE LP","source":"la_county","vote_for":null},"drops":[{"batch_id":1530,"batch_ts":"2026-06-05T16:38:45","candidates":[{"candidate_id":125,"incumbent":null,"is_first_drop":false,"name":"YES","new_votes":156,"new_votes_pct":58.87,"party":"Non Partisan","pct_delta":-0.15,"vote_pct":60.96,"votes":2394},{"candidate_id":126,"incumbent":null,"is_first_drop":false,"name":"NO","new_votes":109,"new_votes_pct":41.13,"party":"Non Partisan","pct_delta":0.15,"vote_pct":39.04,"votes":1533}],"drop_total":3927,"new_votes_in_drop":265,"reporting_pct":null,"source_file":"LA_County_Election_4338-2026-06-05T16-38-45.853.json"},{"batch_id":1445,"batch_ts":"2026-06-04T16:11:55","candidates":[{"candidate_id":125,"incumbent":null,"is_first_drop":false,"name":"YES","new_votes":142,"new_votes_pct":69.61,"party":"Non Partisan","pct_delta":0.5,"vote_pct":61.11,"votes":2238},{"candidate_id":126,"incumbent":null,"is_first_drop":false,"name":"NO","new_votes":62,"new_votes_pct":30.39,"party":"Non Partisan","pct_delta":-0.5,"vote_pct":38.89,"votes":1424}],"drop_total":3662,"new_votes_in_drop":204,"reporting_pct":null,"source_file":"LA_County_Election_4338-2026-06-04T16-11-55.48.json"},{"batch_id":1324,"batch_ts":"2026-06-03T16:07:14","candidates":[{"candidate_id":125,"incumbent":null,"is_first_drop":false,"name":"YES","new_votes":86,"new_votes_pct":56.58,"party":"Non Partisan","pct_delta":-0.19,"vote_pct":60.61,"votes":2096},{"candidate_id":126,"incumbent":null,"is_first_drop":false,"name":"NO","new_votes":66,"new_votes_pct":43.42,"party":"Non Partisan","pct_delta":0.19,"vote_pct":39.39,"votes":1362}],"drop_total":3458,"new_votes_in_drop":152,"reporting_pct":null,"source_file":"LA_County_Election_4338-2026-06-03T16-07-14.883.json"},{"batch_id":1167,"batch_ts":"2026-06-03T02:08:27","candidates":[{"candidate_id":125,"incumbent":null,"is_first_drop":false,"name":"YES","new_votes":5,"new_votes_pct":45.45,"party":"Non Partisan","pct_delta":-0.05,"vote_pct":60.8,"votes":2010},{"candidate_id":126,"incumbent":null,"is_first_drop":false,"name":"NO","new_votes":6,"new_votes_pct":54.55,"party":"Non Partisan","pct_delta":0.05,"vote_pct":39.2,"votes":1296}],"drop_total":3306,"new_votes_in_drop":11,"reporting_pct":null,"source_file":"LA_County_Election_4338-2026-06-03T02-08-27.123.json"},{"batch_id":1142,"batch_ts":"2026-06-03T01:27:31","candidates":[{"candidate_id":125,"incumbent":null,"is_first_drop":false,"name":"YES","new_votes":6,"new_votes_pct":85.71,"party":"Non Partisan","pct_delta":0.05,"vote_pct":60.85,"votes":2005},{"candidate_id":126,"incumbent":null,"is_first_drop":false,"name":"NO","new_votes":1,"new_votes_pct":14.29,"party":"Non Partisan","pct_delta":-0.05,"vote_pct":39.15,"votes":1290}],"drop_total":3295,"new_votes_in_drop":7,"reporting_pct":null,"source_file":"LA_County_Election_4338-2026-06-03T01-27-31.423.json"},{"batch_id":1021,"batch_ts":"2026-06-03T00:51:34","candidates":[{"candidate_id":125,"incumbent":null,"is_first_drop":false,"name":"YES","new_votes":18,"new_votes_pct":66.67,"party":"Non Partisan","pct_delta":0.05,"vote_pct":60.8,"votes":1999},{"candidate_id":126,"incumbent":null,"is_first_drop":false,"name":"NO","new_votes":9,"new_votes_pct":33.33,"party":"Non Partisan","pct_delta":-0.05,"vote_pct":39.2,"votes":1289}],"drop_total":3288,"new_votes_in_drop":27,"reporting_pct":null,"source_file":"LA_County_Election_4338-2026-06-03T00-51-34.797.json"},{"batch_id":984,"batch_ts":"2026-06-03T00:11:21","candidates":[{"candidate_id":125,"incumbent":null,"is_first_drop":false,"name":"YES","new_votes":27,"new_votes_pct":54.0,"party":"Non Partisan","pct_delta":-0.1,"vote_pct":60.75,"votes":1981},{"candidate_id":126,"incumbent":null,"is_first_drop":false,"name":"NO","new_votes":23,"new_votes_pct":46.0,"party":"Non Partisan","pct_delta":0.1,"vote_pct":39.25,"votes":1280}],"drop_total":3261,"new_votes_in_drop":50,"reporting_pct":null,"source_file":"LA_County_Election_4338-2026-06-03T00-11-21.433.json"},{"batch_id":407,"batch_ts":"2026-06-02T23:29:15","candidates":[{"candidate_id":125,"incumbent":null,"is_first_drop":false,"name":"YES","new_votes":352,"new_votes_pct":56.96,"party":"Non Partisan","pct_delta":-0.93,"vote_pct":60.85,"votes":1954},{"candidate_id":126,"incumbent":null,"is_first_drop":false,"name":"NO","new_votes":266,"new_votes_pct":43.04,"party":"Non Partisan","pct_delta":0.93,"vote_pct":39.15,"votes":1257}],"drop_total":3211,"new_votes_in_drop":618,"reporting_pct":null,"source_file":"LA_County_Election_4338-2026-06-02T23-29-15.387.json"},{"batch_id":406,"batch_ts":"2026-06-02T22:50:33","candidates":[{"candidate_id":125,"incumbent":null,"is_first_drop":false,"name":"YES","new_votes":83,"new_votes_pct":70.34,"party":"Non Partisan","pct_delta":0.41,"vote_pct":61.78,"votes":1602},{"candidate_id":126,"incumbent":null,"is_first_drop":false,"name":"NO","new_votes":35,"new_votes_pct":29.66,"party":"Non Partisan","pct_delta":-0.41,"vote_pct":38.22,"votes":991}],"drop_total":2593,"new_votes_in_drop":118,"reporting_pct":null,"source_file":"LA_County_Election_4338-2026-06-02T22-50-33.983.json"},{"batch_id":321,"batch_ts":"2026-06-02T22:17:30","candidates":[{"candidate_id":125,"incumbent":null,"is_first_drop":false,"name":"YES","new_votes":12,"new_votes_pct":50.0,"party":"Non Partisan","pct_delta":-0.12,"vote_pct":61.37,"votes":1519},{"candidate_id":126,"incumbent":null,"is_first_drop":false,"name":"NO","new_votes":12,"new_votes_pct":50.0,"party":"Non Partisan","pct_delta":0.12,"vote_pct":38.63,"votes":956}],"drop_total":2475,"new_votes_in_drop":24,"reporting_pct":null,"source_file":"LA_County_Election_4338-2026-06-02T22-17-30.85.json"},{"batch_id":140,"batch_ts":"2026-06-02T21:33:40","candidates":[{"candidate_id":125,"incumbent":null,"is_first_drop":false,"name":"YES","new_votes":25,"new_votes_pct":62.5,"party":"Non Partisan","pct_delta":0.02,"vote_pct":61.49,"votes":1507},{"candidate_id":126,"incumbent":null,"is_first_drop":false,"name":"NO","new_votes":15,"new_votes_pct":37.5,"party":"Non Partisan","pct_delta":-0.02,"vote_pct":38.51,"votes":944}],"drop_total":2451,"new_votes_in_drop":40,"reporting_pct":null,"source_file":"LA_County_Election_4338-2026-06-02T21-33-40.73.json"},{"batch_id":139,"batch_ts":"2026-06-02T21:18:00","candidates":[{"candidate_id":125,"incumbent":null,"is_first_drop":false,"name":"YES","new_votes":25,"new_votes_pct":80.65,"party":"Non Partisan","pct_delta":0.25,"vote_pct":61.47,"votes":1482},{"candidate_id":126,"incumbent":null,"is_first_drop":false,"name":"NO","new_votes":6,"new_votes_pct":19.35,"party":"Non Partisan","pct_delta":-0.25,"vote_pct":38.53,"votes":929}],"drop_total":2411,"new_votes_in_drop":31,"reporting_pct":null,"source_file":"LA_County_Election_4338-2026-06-02T21-18-00.383.json"},{"batch_id":90,"batch_ts":"2026-06-02T20:48:40","candidates":[{"candidate_id":125,"incumbent":null,"is_first_drop":false,"name":"YES","new_votes":27,"new_votes_pct":58.7,"party":"Non Partisan","pct_delta":-0.05,"vote_pct":61.22,"votes":1457},{"candidate_id":126,"incumbent":null,"is_first_drop":false,"name":"NO","new_votes":19,"new_votes_pct":41.3,"party":"Non Partisan","pct_delta":0.05,"vote_pct":38.78,"votes":923}],"drop_total":2380,"new_votes_in_drop":46,"reporting_pct":null,"source_file":"LA_County_Election_4338-2026-06-02T20-48-40.927.json"},{"batch_id":16,"batch_ts":"2026-06-02T20:31:50","candidates":[{"candidate_id":125,"incumbent":null,"is_first_drop":false,"name":"YES","new_votes":188,"new_votes_pct":53.87,"party":"Non Partisan","pct_delta":-1.3,"vote_pct":61.27,"votes":1430},{"candidate_id":126,"incumbent":null,"is_first_drop":false,"name":"NO","new_votes":161,"new_votes_pct":46.13,"party":"Non Partisan","pct_delta":1.3,"vote_pct":38.73,"votes":904}],"drop_total":2334,"new_votes_in_drop":349,"reporting_pct":null,"source_file":"LA_County_Election_4338-2026-06-02T20-31-50.377.json"},{"batch_id":15,"batch_ts":"2026-06-02T20:15:15","candidates":[{"candidate_id":125,"incumbent":null,"is_first_drop":false,"name":"YES","new_votes":1242,"new_votes_pct":62.57,"party":"Non Partisan","pct_delta":62.57,"vote_pct":62.57,"votes":1242},{"candidate_id":126,"incumbent":null,"is_first_drop":false,"name":"NO","new_votes":743,"new_votes_pct":37.43,"party":"Non Partisan","pct_delta":37.43,"vote_pct":37.43,"votes":743}],"drop_total":1985,"new_votes_in_drop":1985,"reporting_pct":null,"source_file":"LA_County_Election_4338-2026-06-02T20-15-15.75.json"},{"batch_id":2,"batch_ts":"2026-05-26T16:54:13","candidates":[{"candidate_id":125,"incumbent":null,"is_first_drop":true,"name":"YES","new_votes":0,"new_votes_pct":0.0,"party":"Non Partisan","pct_delta":0.0,"vote_pct":0.0,"votes":0},{"candidate_id":126,"incumbent":null,"is_first_drop":true,"name":"NO","new_votes":0,"new_votes_pct":0.0,"party":"Non Partisan","pct_delta":0.0,"vote_pct":0.0,"votes":0}],"drop_total":0,"new_votes_in_drop":0,"reporting_pct":null,"source_file":"LA_County_Election_4338-2026-05-26T16-54-13.63.json"}]}